cerrax/__init__.py
cerrax/dotdict.py
cerrax/grid.py
cerrax/indentread.py
cerrax/indexedobj.py
cerrax_py-1.1.0.dist-info/METADATA
cerrax_py-1.1.0.dist-info/WHEEL
cerrax_py-1.1.0.dist-info/RECORD
