Metadata-Version: 2.3
Name: cerrax-py
Version: 1.1.0
Summary: A collection of different modules for Python that make life a little bit easier.
License: BSD-2-Clause
Author: Charlie Koch
Author-email: charles@cerrax.com
Requires-Python: >=3.9,<4.0
Classifier: License :: OSI Approved :: BSD License
Classifier: Programming Language :: Python :: 3
Classifier: Programming Language :: Python :: 3.9
Classifier: Programming Language :: Python :: 3.10
Classifier: Programming Language :: Python :: 3.11
Classifier: Programming Language :: Python :: 3.12
Classifier: Programming Language :: Python :: 3.13
Project-URL: Homepage, http://cerrax.com
Project-URL: Repository, https://gitlab.com/charles.w.koch/cerrax-python-utilities
